BreezeHistoricalOptions/Breezy.py
BreezeHistoricalOptions/__init__.py
BreezeHistoricalOptions/autologin.py
BreezeHistoricalOptions/unifunc.py
breeze_historical_options-1.2.dist-info/METADATA
breeze_historical_options-1.2.dist-info/WHEEL
breeze_historical_options-1.2.dist-info/top_level.txt
breeze_historical_options-1.2.dist-info/RECORD
